setup.py
uhashlib.py
micropython_cpython_uhashlib.egg-info/PKG-INFO
micropython_cpython_uhashlib.egg-info/SOURCES.txt
micropython_cpython_uhashlib.egg-info/dependency_links.txt
micropython_cpython_uhashlib.egg-info/top_level.txt