Metadata-Version: 1.0
Name: micropython-cpython-uhashlib
Version: 0.1
Summary: MicroPython module uhashlib ported to CPython
Home-page: https://github.com/pfalcon/micropython-lib
Author: Paul Sokolovsky
Author-email: micropython-lib@googlegroups.com
License: Python
Platform: UNKNOWN
